{"moduleDefinition":{"range":[1,1,1,27],"value":{"type":"normal","normal":{"moduleName":{"range":[1,8,1,13],"value":["Model"]},"exposingList":{"range":[1,14,1,27],"value":{"type":"all","all":[1,24,1,26]}}}}},"imports":[{"range":[2,1,2,32],"value":{"moduleName":{"range":[2,8,2,13],"value":["Heros"]},"moduleAlias":null,"exposingList":{"range":[2,14,2,32],"value":{"type":"explicit","explicit":[{"range":[2,24,2,31],"value":{"type":"typeOrAlias","typeOrAlias":{"name":"Teacher"}}}]}}}}],"declarations":[{"range":[3,1,8,6],"value":{"type":"typeAlias","typeAlias":{"documentation":null,"name":{"range":[3,12,3,15],"value":"Rec"},"generics":[],"typeAnnotation":{"range":[4,5,8,6],"value":{"type":"record","record":{"value":[{"range":[4,7,4,17],"value":{"name":{"range":[4,7,4,9],"value":"cx"},"typeAnnotation":{"range":[4,12,4,17],"value":{"type":"typed","typed":{"moduleNameAndName":{"range":[4,12,4,17],"value":{"moduleName":[],"name":"Float"}},"args":[]}}}}},{"range":[5,5,6,5],"value":{"name":{"range":[5,7,5,9],"value":"cy"},"typeAnnotation":{"range":[5,12,5,17],"value":{"type":"typed","typed":{"moduleNameAndName":{"range":[5,12,5,17],"value":{"moduleName":[],"name":"Float"}},"args":[]}}}}},{"range":[6,5,7,5],"value":{"name":{"range":[6,7,6,16],"value":"halfWidth"},"typeAnnotation":{"range":[6,19,6,24],"value":{"type":"typed","typed":{"moduleNameAndName":{"range":[6,19,6,24],"value":{"moduleName":[],"name":"Float"}},"args":[]}}}}},{"range":[7,5,8,5],"value":{"name":{"range":[7,7,7,17],"value":"halfHeight"},"typeAnnotation":{"range":[7,20,7,25],"value":{"type":"typed","typed":{"moduleNameAndName":{"range":[7,20,7,25],"value":{"moduleName":[],"name":"Float"}},"args":[]}}}}}]}}}}}},{"range":[10,1,13,18],"value":{"type":"typedecl","typedecl":{"documentation":null,"name":{"range":[10,6,10,19],"value":"Collisiontype"},"generics":[],"constructors":[{"range":[11,7,11,14],"value":{"name":{"range":[11,7,11,14],"value":"Horizon"},"arguments":[]}},{"range":[12,7,12,15],"value":{"name":{"range":[12,7,12,15],"value":"Vertical"},"arguments":[]}},{"range":[13,7,13,18],"value":{"name":{"range":[13,7,13,18],"value":"Nocollision"},"arguments":[]}}]}}},{"range":[16,1,25,1],"value":{"type":"function","function":{"documentation":null,"signature":{"range":[16,1,16,47],"value":{"name":{"range":[16,1,16,17],"value":"recCollisionTest"},"typeAnnotation":{"range":[16,20,16,47],"value":{"type":"function","function":{"left":{"range":[16,20,16,23],"value":{"type":"typed","typed":{"moduleNameAndName":{"range":[16,20,16,23],"value":{"moduleName":[],"name":"Rec"}},"args":[]}}},"right":{"range":[16,27,16,47],"value":{"type":"function","function":{"left":{"range":[16,27,16,30],"value":{"type":"typed","typed":{"moduleNameAndName":{"range":[16,27,16,30],"value":{"moduleName":[],"name":"Rec"}},"args":[]}}},"right":{"range":[16,34,16,47],"value":{"type":"typed","typed":{"moduleNameAndName":{"range":[16,34,16,47],"value":{"moduleName":[],"name":"Collisiontype"}},"args":[]}}}}}}}}}}},"declaration":{"range":[17,1,25,1],"value":{"name":{"range":[17,1,17,17],"value":"recCollisionTest"},"arguments":[{"range":[17,18,17,22],"value":{"type":"var","var":{"value":"rec1"}}},{"range":[17,23,17,27],"value":{"type":"var","var":{"value":"rec2"}}}],"expression":{"range":[18,5,25,1],"value":{"type":"ifBlock","ifBlock":{"clause":{"range":[18,8,18,219],"value":{"type":"application","application":[{"range":[18,8,18,66],"value":{"type":"parenthesized","parenthesized":{"range":[18,9,18,65],"value":{"type":"application","application":[{"range":[18,9,18,12],"value":{"type":"functionOrValue","functionOrValue":{"moduleName":[],"name":"abs"}}},{"range":[18,12,18,31],"value":{"type":"parenthesized","parenthesized":{"range":[18,17,18,30],"value":{"type":"application","application":[{"range":[18,17,18,20],"value":{"type":"recordAccess","recordAccess":{"expression":{"range":[18,13,18,17],"value":{"type":"functionOrValue","functionOrValue":{"moduleName":[],"name":"rec1"}}},"name":{"range":[18,18,18,20],"value":"cx"}}}},{"range":[18,21,18,23],"value":{"type":"operator","operator":"-"}},{"range":[18,27,18,30],"value":{"type":"recordAccess","recordAccess":{"expression":{"range":[18,23,18,27],"value":{"type":"functionOrValue","functionOrValue":{"moduleName":[],"name":"rec2"}}},"name":{"range":[18,28,18,30],"value":"cx"}}}}]}}}},{"range":[18,32,18,33],"value":{"type":"operator","operator":"<"}},{"range":[18,38,18,48],"value":{"type":"recordAccess","recordAccess":{"expression":{"range":[18,34,18,38],"value":{"type":"functionOrValue","functionOrValue":{"moduleName":[],"name":"rec1"}}},"name":{"range":[18,39,18,48],"value":"halfWidth"}}}},{"range":[18,49,18,50],"value":{"type":"operator","operator":"+"}},{"range":[18,55,18,65],"value":{"type":"recordAccess","recordAccess":{"expression":{"range":[18,51,18,55],"value":{"type":"functionOrValue","functionOrValue":{"moduleName":[],"name":"rec2"}}},"name":{"range":[18,56,18,65],"value":"halfWidth"}}}}]}}}},{"range":[18,67,18,69],"value":{"type":"operator","operator":"&&"}},{"range":[18,70,18,130],"value":{"type":"parenthesized","parenthesized":{"range":[18,71,18,129],"value":{"type":"application","application":[{"range":[18,71,18,74],"value":{"type":"functionOrValue","functionOrValue":{"moduleName":[],"name":"abs"}}},{"range":[18,74,18,93],"value":{"type":"parenthesized","parenthesized":{"range":[18,79,18,92],"value":{"type":"application","application":[{"range":[18,79,18,82],"value":{"type":"recordAccess","recordAccess":{"expression":{"range":[18,75,18,79],"value":{"type":"functionOrValue","functionOrValue":{"moduleName":[],"name":"rec1"}}},"name":{"range":[18,80,18,82],"value":"cy"}}}},{"range":[18,83,18,85],"value":{"type":"operator","operator":"-"}},{"range":[18,89,18,92],"value":{"type":"recordAccess","recordAccess":{"expression":{"range":[18,85,18,89],"value":{"type":"functionOrValue","functionOrValue":{"moduleName":[],"name":"rec2"}}},"name":{"range":[18,90,18,92],"value":"cy"}}}}]}}}},{"range":[18,94,18,95],"value":{"type":"operator","operator":"<"}},{"range":[18,100,18,111],"value":{"type":"recordAccess","recordAccess":{"expression":{"range":[18,96,18,100],"value":{"type":"functionOrValue","functionOrValue":{"moduleName":[],"name":"rec1"}}},"name":{"range":[18,101,18,111],"value":"halfHeight"}}}},{"range":[18,112,18,113],"value":{"type":"operator","operator":"+"}},{"range":[18,118,18,129],"value":{"type":"recordAccess","recordAccess":{"expression":{"range":[18,114,18,118],"value":{"type":"functionOrValue","functionOrValue":{"moduleName":[],"name":"rec2"}}},"name":{"range":[18,119,18,129],"value":"halfHeight"}}}}]}}}},{"range":[18,131,18,133],"value":{"type":"operator","operator":"&&"}},{"range":[18,134,18,219],"value":{"type":"parenthesized","parenthesized":{"range":[18,135,18,218],"value":{"type":"application","application":[{"range":[18,135,18,138],"value":{"type":"functionOrValue","functionOrValue":{"moduleName":[],"name":"abs"}}},{"range":[18,138,18,157],"value":{"type":"parenthesized","parenthesized":{"range":[18,143,18,156],"value":{"type":"application","application":[{"range":[18,143,18,146],"value":{"type":"recordAccess","recordAccess":{"expression":{"range":[18,139,18,143],"value":{"type":"functionOrValue","functionOrValue":{"moduleName":[],"name":"rec1"}}},"name":{"range":[18,144,18,146],"value":"cx"}}}},{"range":[18,147,18,149],"value":{"type":"operator","operator":"-"}},{"range":[18,153,18,156],"value":{"type":"recordAccess","recordAccess":{"expression":{"range":[18,149,18,153],"value":{"type":"functionOrValue","functionOrValue":{"moduleName":[],"name":"rec2"}}},"name":{"range":[18,154,18,156],"value":"cx"}}}}]}}}},{"range":[18,158,18,160],"value":{"type":"operator","operator":"-"}},{"range":[18,164,18,174],"value":{"type":"recordAccess","recordAccess":{"expression":{"range":[18,160,18,164],"value":{"type":"functionOrValue","functionOrValue":{"moduleName":[],"name":"rec1"}}},"name":{"range":[18,165,18,174],"value":"halfWidth"}}}},{"range":[18,175,18,177],"value":{"type":"operator","operator":">="}},{"range":[18,178,18,181],"value":{"type":"functionOrValue","functionOrValue":{"moduleName":[],"name":"abs"}}},{"range":[18,181,18,200],"value":{"type":"parenthesized","parenthesized":{"range":[18,186,18,199],"value":{"type":"application","application":[{"range":[18,186,18,189],"value":{"type":"recordAccess","recordAccess":{"expression":{"range":[18,182,18,186],"value":{"type":"functionOrValue","functionOrValue":{"moduleName":[],"name":"rec1"}}},"name":{"range":[18,187,18,189],"value":"cy"}}}},{"range":[18,190,18,192],"value":{"type":"operator","operator":"-"}},{"range":[18,196,18,199],"value":{"type":"recordAccess","recordAccess":{"expression":{"range":[18,192,18,196],"value":{"type":"functionOrValue","functionOrValue":{"moduleName":[],"name":"rec2"}}},"name":{"range":[18,197,18,199],"value":"cy"}}}}]}}}},{"range":[18,201,18,203],"value":{"type":"operator","operator":"-"}},{"range":[18,207,18,218],"value":{"type":"recordAccess","recordAccess":{"expression":{"range":[18,203,18,207],"value":{"type":"functionOrValue","functionOrValue":{"moduleName":[],"name":"rec1"}}},"name":{"range":[18,208,18,218],"value":"halfHeight"}}}}]}}}}]}},"then":{"range":[19,9,19,16],"value":{"type":"functionOrValue","functionOrValue":{"moduleName":[],"name":"Horizon"}}},"else":{"range":[20,10,25,1],"value":{"type":"ifBlock","ifBlock":{"clause":{"range":[20,13,20,135],"value":{"type":"application","application":[{"range":[20,13,20,71],"value":{"type":"parenthesized","parenthesized":{"range":[20,14,20,70],"value":{"type":"application","application":[{"range":[20,14,20,17],"value":{"type":"functionOrValue","functionOrValue":{"moduleName":[],"name":"abs"}}},{"range":[20,17,20,36],"value":{"type":"parenthesized","parenthesized":{"range":[20,22,20,35],"value":{"type":"application","application":[{"range":[20,22,20,25],"value":{"type":"recordAccess","recordAccess":{"expression":{"range":[20,18,20,22],"value":{"type":"functionOrValue","functionOrValue":{"moduleName":[],"name":"rec1"}}},"name":{"range":[20,23,20,25],"value":"cx"}}}},{"range":[20,26,20,28],"value":{"type":"operator","operator":"-"}},{"range":[20,32,20,35],"value":{"type":"recordAccess","recordAccess":{"expression":{"range":[20,28,20,32],"value":{"type":"functionOrValue","functionOrValue":{"moduleName":[],"name":"rec2"}}},"name":{"range":[20,33,20,35],"value":"cx"}}}}]}}}},{"range":[20,37,20,38],"value":{"type":"operator","operator":"<"}},{"range":[20,43,20,53],"value":{"type":"recordAccess","recordAccess":{"expression":{"range":[20,39,20,43],"value":{"type":"functionOrValue","functionOrValue":{"moduleName":[],"name":"rec1"}}},"name":{"range":[20,44,20,53],"value":"halfWidth"}}}},{"range":[20,54,20,55],"value":{"type":"operator","operator":"+"}},{"range":[20,60,20,70],"value":{"type":"recordAccess","recordAccess":{"expression":{"range":[20,56,20,60],"value":{"type":"functionOrValue","functionOrValue":{"moduleName":[],"name":"rec2"}}},"name":{"range":[20,61,20,70],"value":"halfWidth"}}}}]}}}},{"range":[20,72,20,74],"value":{"type":"operator","operator":"&&"}},{"range":[20,75,20,135],"value":{"type":"parenthesized","parenthesized":{"range":[20,76,20,134],"value":{"type":"application","application":[{"range":[20,76,20,79],"value":{"type":"functionOrValue","functionOrValue":{"moduleName":[],"name":"abs"}}},{"range":[20,79,20,98],"value":{"type":"parenthesized","parenthesized":{"range":[20,84,20,97],"value":{"type":"application","application":[{"range":[20,84,20,87],"value":{"type":"recordAccess","recordAccess":{"expression":{"range":[20,80,20,84],"value":{"type":"functionOrValue","functionOrValue":{"moduleName":[],"name":"rec1"}}},"name":{"range":[20,85,20,87],"value":"cy"}}}},{"range":[20,88,20,90],"value":{"type":"operator","operator":"-"}},{"range":[20,94,20,97],"value":{"type":"recordAccess","recordAccess":{"expression":{"range":[20,90,20,94],"value":{"type":"functionOrValue","functionOrValue":{"moduleName":[],"name":"rec2"}}},"name":{"range":[20,95,20,97],"value":"cy"}}}}]}}}},{"range":[20,99,20,100],"value":{"type":"operator","operator":"<"}},{"range":[20,105,20,116],"value":{"type":"recordAccess","recordAccess":{"expression":{"range":[20,101,20,105],"value":{"type":"functionOrValue","functionOrValue":{"moduleName":[],"name":"rec1"}}},"name":{"range":[20,106,20,116],"value":"halfHeight"}}}},{"range":[20,117,20,118],"value":{"type":"operator","operator":"+"}},{"range":[20,123,20,134],"value":{"type":"recordAccess","recordAccess":{"expression":{"range":[20,119,20,123],"value":{"type":"functionOrValue","functionOrValue":{"moduleName":[],"name":"rec2"}}},"name":{"range":[20,124,20,134],"value":"halfHeight"}}}}]}}}}]}},"then":{"range":[21,9,21,17],"value":{"type":"functionOrValue","functionOrValue":{"moduleName":[],"name":"Vertical"}}},"else":{"range":[23,9,23,20],"value":{"type":"functionOrValue","functionOrValue":{"moduleName":[],"name":"Nocollision"}}}}}}}}}}}}}},{"range":[25,1,26,22],"value":{"type":"function","function":{"documentation":null,"signature":{"range":[25,1,25,14],"value":{"name":{"range":[25,1,25,8],"value":"recInit"},"typeAnnotation":{"range":[25,11,25,14],"value":{"type":"typed","typed":{"moduleNameAndName":{"range":[25,11,25,14],"value":{"moduleName":[],"name":"Rec"}},"args":[]}}}}},"declaration":{"range":[26,1,26,22],"value":{"name":{"range":[26,1,26,8],"value":"recInit"},"arguments":[],"expression":{"range":[26,11,26,22],"value":{"type":"application","application":[{"range":[26,11,26,14],"value":{"type":"functionOrValue","functionOrValue":{"moduleName":[],"name":"Rec"}}},{"range":[26,15,26,16],"value":{"type":"integer","integer":0}},{"range":[26,17,26,18],"value":{"type":"integer","integer":0}},{"range":[26,19,26,20],"value":{"type":"integer","integer":0}},{"range":[26,21,26,22],"value":{"type":"integer","integer":0}}]}}}}}}},{"range":[28,1,35,6],"value":{"type":"typeAlias","typeAlias":{"documentation":null,"name":{"range":[28,12,28,17],"value":"Brick"},"generics":[],"typeAnnotation":{"range":[29,5,35,6],"value":{"type":"record","record":{"value":[{"range":[29,7,29,16],"value":{"name":{"range":[29,7,29,8],"value":"x"},"typeAnnotation":{"range":[29,11,29,16],"value":{"type":"typed","typed":{"moduleNameAndName":{"range":[29,11,29,16],"value":{"moduleName":[],"name":"Float"}},"args":[]}}}}},{"range":[30,5,31,5],"value":{"name":{"range":[30,7,30,8],"value":"y"},"typeAnnotation":{"range":[30,11,30,16],"value":{"type":"typed","typed":{"moduleNameAndName":{"range":[30,11,30,16],"value":{"moduleName":[],"name":"Float"}},"args":[]}}}}},{"range":[31,5,32,5],"value":{"name":{"range":[31,7,31,12],"value":"width"},"typeAnnotation":{"range":[31,15,31,20],"value":{"type":"typed","typed":{"moduleNameAndName":{"range":[31,15,31,20],"value":{"moduleName":[],"name":"Float"}},"args":[]}}}}},{"range":[32,5,33,5],"value":{"name":{"range":[32,7,32,13],"value":"height"},"typeAnnotation":{"range":[32,16,32,21],"value":{"type":"typed","typed":{"moduleNameAndName":{"range":[32,16,32,21],"value":{"moduleName":[],"name":"Float"}},"args":[]}}}}},{"range":[33,5,34,5],"value":{"name":{"range":[33,7,33,11],"value":"edge"},"typeAnnotation":{"range":[33,14,33,17],"value":{"type":"typed","typed":{"moduleNameAndName":{"range":[33,14,33,17],"value":{"moduleName":[],"name":"Rec"}},"args":[]}}}}},{"range":[34,5,35,5],"value":{"name":{"range":[34,7,34,16],"value":"collision"},"typeAnnotation":{"range":[34,19,34,23],"value":{"type":"typed","typed":{"moduleNameAndName":{"range":[34,19,34,23],"value":{"moduleName":[],"name":"Bool"}},"args":[]}}}}}]}}}}}},{"range":[37,1,44,6],"value":{"type":"typeAlias","typeAlias":{"documentation":null,"name":{"range":[37,12,37,15],"value":"Bat"},"generics":[],"typeAnnotation":{"range":[38,5,44,6],"value":{"type":"record","record":{"value":[{"range":[38,7,38,16],"value":{"name":{"range":[38,7,38,8],"value":"x"},"typeAnnotation":{"range":[38,11,38,16],"value":{"type":"typed","typed":{"moduleNameAndName":{"range":[38,11,38,16],"value":{"moduleName":[],"name":"Float"}},"args":[]}}}}},{"range":[39,5,40,5],"value":{"name":{"range":[39,7,39,8],"value":"y"},"typeAnnotation":{"range":[39,11,39,16],"value":{"type":"typed","typed":{"moduleNameAndName":{"range":[39,11,39,16],"value":{"moduleName":[],"name":"Float"}},"args":[]}}}}},{"range":[40,5,41,5],"value":{"name":{"range":[40,7,40,12],"value":"width"},"typeAnnotation":{"range":[40,15,40,20],"value":{"type":"typed","typed":{"moduleNameAndName":{"range":[40,15,40,20],"value":{"moduleName":[],"name":"Float"}},"args":[]}}}}},{"range":[41,5,42,5],"value":{"name":{"range":[41,7,41,13],"value":"height"},"typeAnnotation":{"range":[41,16,41,21],"value":{"type":"typed","typed":{"moduleNameAndName":{"range":[41,16,41,21],"value":{"moduleName":[],"name":"Float"}},"args":[]}}}}},{"range":[42,5,43,5],"value":{"name":{"range":[42,7,42,11],"value":"edge"},"typeAnnotation":{"range":[42,14,42,17],"value":{"type":"typed","typed":{"moduleNameAndName":{"range":[42,14,42,17],"value":{"moduleName":[],"name":"Rec"}},"args":[]}}}}},{"range":[43,5,44,5],"value":{"name":{"range":[43,7,43,13],"value":"xSpeed"},"typeAnnotation":{"range":[43,16,43,21],"value":{"type":"typed","typed":{"moduleNameAndName":{"range":[43,16,43,21],"value":{"moduleName":[],"name":"Float"}},"args":[]}}}}}]}}}}}},{"range":[46,1,53,6],"value":{"type":"typeAlias","typeAlias":{"documentation":null,"name":{"range":[46,12,46,16],"value":"Ball"},"generics":[],"typeAnnotation":{"range":[47,5,53,6],"value":{"type":"record","record":{"value":[{"range":[47,7,47,16],"value":{"name":{"range":[47,7,47,8],"value":"x"},"typeAnnotation":{"range":[47,11,47,16],"value":{"type":"typed","typed":{"moduleNameAndName":{"range":[47,11,47,16],"value":{"moduleName":[],"name":"Float"}},"args":[]}}}}},{"range":[48,5,49,5],"value":{"name":{"range":[48,7,48,8],"value":"y"},"typeAnnotation":{"range":[48,11,48,16],"value":{"type":"typed","typed":{"moduleNameAndName":{"range":[48,11,48,16],"value":{"moduleName":[],"name":"Float"}},"args":[]}}}}},{"range":[49,5,50,5],"value":{"name":{"range":[49,7,49,8],"value":"r"},"typeAnnotation":{"range":[49,11,49,16],"value":{"type":"typed","typed":{"moduleNameAndName":{"range":[49,11,49,16],"value":{"moduleName":[],"name":"Float"}},"args":[]}}}}},{"range":[50,5,51,5],"value":{"name":{"range":[50,7,50,11],"value":"edge"},"typeAnnotation":{"range":[50,14,50,17],"value":{"type":"typed","typed":{"moduleNameAndName":{"range":[50,14,50,17],"value":{"moduleName":[],"name":"Rec"}},"args":[]}}}}},{"range":[51,5,52,5],"value":{"name":{"range":[51,7,51,13],"value":"xSpeed"},"typeAnnotation":{"range":[51,16,51,21],"value":{"type":"typed","typed":{"moduleNameAndName":{"range":[51,16,51,21],"value":{"moduleName":[],"name":"Float"}},"args":[]}}}}},{"range":[52,5,53,5],"value":{"name":{"range":[52,7,52,13],"value":"ySpeed"},"typeAnnotation":{"range":[52,16,52,21],"value":{"type":"typed","typed":{"moduleNameAndName":{"range":[52,16,52,21],"value":{"moduleName":[],"name":"Float"}},"args":[]}}}}}]}}}}}},{"range":[55,1,68,6],"value":{"type":"typeAlias","typeAlias":{"documentation":null,"name":{"range":[55,12,55,18],"value":"Player"},"generics":[],"typeAnnotation":{"range":[56,5,68,6],"value":{"type":"record","record":{"value":[{"range":[58,7,58,18],"value":{"name":{"range":[58,7,58,11],"value":"ball"},"typeAnnotation":{"range":[58,14,58,18],"value":{"type":"typed","typed":{"moduleNameAndName":{"range":[58,14,58,18],"value":{"moduleName":[],"name":"Ball"}},"args":[]}}}}},{"range":[59,5,60,5],"value":{"name":{"range":[59,7,59,10],"value":"bat"},"typeAnnotation":{"range":[59,14,59,17],"value":{"type":"typed","typed":{"moduleNameAndName":{"range":[59,14,59,17],"value":{"moduleName":[],"name":"Bat"}},"args":[]}}}}},{"range":[60,5,61,5],"value":{"name":{"range":[60,7,60,13],"value":"bricks"},"typeAnnotation":{"range":[60,16,60,26],"value":{"type":"typed","typed":{"moduleNameAndName":{"range":[60,16,60,20],"value":{"moduleName":[],"name":"List"}},"args":[{"range":[60,21,60,26],"value":{"type":"typed","typed":{"moduleNameAndName":{"range":[60,21,60,26],"value":{"moduleName":[],"name":"Brick"}},"args":[]}}}]}}}}},{"range":[61,5,62,5],"value":{"name":{"range":[61,7,61,15],"value":"moveLeft"},"typeAnnotation":{"range":[61,18,61,22],"value":{"type":"typed","typed":{"moduleNameAndName":{"range":[61,18,61,22],"value":{"moduleName":[],"name":"Bool"}},"args":[]}}}}},{"range":[62,5,63,5],"value":{"name":{"range":[62,7,62,16],"value":"moveRight"},"typeAnnotation":{"range":[62,19,62,23],"value":{"type":"typed","typed":{"moduleNameAndName":{"range":[62,19,62,23],"value":{"moduleName":[],"name":"Bool"}},"args":[]}}}}},{"range":[63,5,64,5],"value":{"name":{"range":[63,7,63,11],"value":"lose"},"typeAnnotation":{"range":[63,14,63,18],"value":{"type":"typed","typed":{"moduleNameAndName":{"range":[63,14,63,18],"value":{"moduleName":[],"name":"Bool"}},"args":[]}}}}},{"range":[64,5,65,5],"value":{"name":{"range":[64,7,64,16],"value":"direction"},"typeAnnotation":{"range":[64,19,64,24],"value":{"type":"typed","typed":{"moduleNameAndName":{"range":[64,19,64,24],"value":{"moduleName":[],"name":"Float"}},"args":[]}}}}},{"range":[65,5,68,5],"value":{"name":{"range":[65,7,65,15],"value":"teachers"},"typeAnnotation":{"range":[65,18,65,30],"value":{"type":"typed","typed":{"moduleNameAndName":{"range":[65,18,65,22],"value":{"moduleName":[],"name":"List"}},"args":[{"range":[65,23,65,30],"value":{"type":"typed","typed":{"moduleNameAndName":{"range":[65,23,65,30],"value":{"moduleName":[],"name":"Teacher"}},"args":[]}}}]}}}}}]}}}}}},{"range":[70,1,73,6],"value":{"type":"typeAlias","typeAlias":{"documentation":null,"name":{"range":[70,12,70,17],"value":"Model"},"generics":[],"typeAnnotation":{"range":[71,5,73,6],"value":{"type":"record","record":{"value":[{"range":[71,7,71,23],"value":{"name":{"range":[71,7,71,14],"value":"player1"},"typeAnnotation":{"range":[71,17,71,23],"value":{"type":"typed","typed":{"moduleNameAndName":{"range":[71,17,71,23],"value":{"moduleName":[],"name":"Player"}},"args":[]}}}}},{"range":[72,5,73,5],"value":{"name":{"range":[72,7,72,14],"value":"player2"},"typeAnnotation":{"range":[72,17,72,23],"value":{"type":"typed","typed":{"moduleNameAndName":{"range":[72,17,72,23],"value":{"moduleName":[],"name":"Player"}},"args":[]}}}}}]}}}}}},{"range":[75,1,76,51],"value":{"type":"function","function":{"documentation":null,"signature":{"range":[75,1,75,20],"value":{"name":{"range":[75,1,75,12],"value":"brickConfig"},"typeAnnotation":{"range":[75,15,75,20],"value":{"type":"typed","typed":{"moduleNameAndName":{"range":[75,15,75,20],"value":{"moduleName":[],"name":"Brick"}},"args":[]}}}}},"declaration":{"range":[76,1,76,51],"value":{"name":{"range":[76,1,76,12],"value":"brickConfig"},"arguments":[],"expression":{"range":[76,15,76,51],"value":{"type":"application","application":[{"range":[76,15,76,20],"value":{"type":"functionOrValue","functionOrValue":{"moduleName":[],"name":"Brick"}}},{"range":[76,21,76,22],"value":{"type":"integer","integer":0}},{"range":[76,23,76,24],"value":{"type":"integer","integer":0}},{"range":[76,25,76,31],"value":{"type":"parenthesized","parenthesized":{"range":[76,26,76,30],"value":{"type":"application","application":[{"range":[76,26,76,28],"value":{"type":"integer","integer":10}},{"range":[76,28,76,29],"value":{"type":"operator","operator":"/"}},{"range":[76,29,76,30],"value":{"type":"integer","integer":2}}]}}}},{"range":[76,32,76,37],"value":{"type":"parenthesized","parenthesized":{"range":[76,33,76,36],"value":{"type":"application","application":[{"range":[76,33,76,34],"value":{"type":"integer","integer":4}},{"range":[76,34,76,35],"value":{"type":"operator","operator":"/"}},{"range":[76,35,76,36],"value":{"type":"integer","integer":2}}]}}}},{"range":[76,38,76,45],"value":{"type":"functionOrValue","functionOrValue":{"moduleName":[],"name":"recInit"}}},{"range":[76,46,76,51],"value":{"type":"functionOrValue","functionOrValue":{"moduleName":[],"name":"False"}}}]}}}}}}},{"range":[80,1,81,55],"value":{"type":"function","function":{"documentation":null,"signature":{"range":[80,1,80,16],"value":{"name":{"range":[80,1,80,10],"value":"batConfig"},"typeAnnotation":{"range":[80,13,80,16],"value":{"type":"typed","typed":{"moduleNameAndName":{"range":[80,13,80,16],"value":{"moduleName":[],"name":"Bat"}},"args":[]}}}}},"declaration":{"range":[81,1,81,55],"value":{"name":{"range":[81,1,81,10],"value":"batConfig"},"arguments":[],"expression":{"range":[81,13,81,55],"value":{"type":"application","application":[{"range":[81,13,81,16],"value":{"type":"functionOrValue","functionOrValue":{"moduleName":[],"name":"Bat"}}},{"range":[81,17,81,23],"value":{"type":"parenthesized","parenthesized":{"range":[81,18,81,22],"value":{"type":"application","application":[{"range":[81,18,81,20],"value":{"type":"integer","integer":45}},{"range":[81,20,81,21],"value":{"type":"operator","operator":"/"}},{"range":[81,21,81,22],"value":{"type":"integer","integer":2}}]}}}},{"range":[81,24,81,30],"value":{"type":"parenthesized","parenthesized":{"range":[81,25,81,29],"value":{"type":"application","application":[{"range":[81,25,81,27],"value":{"type":"integer","integer":70}},{"range":[81,27,81,28],"value":{"type":"operator","operator":"/"}},{"range":[81,28,81,29],"value":{"type":"integer","integer":2}}]}}}},{"range":[81,31,81,37],"value":{"type":"parenthesized","parenthesized":{"range":[81,32,81,36],"value":{"type":"application","application":[{"range":[81,32,81,34],"value":{"type":"integer","integer":20}},{"range":[81,34,81,35],"value":{"type":"operator","operator":"/"}},{"range":[81,35,81,36],"value":{"type":"integer","integer":2}}]}}}},{"range":[81,38,81,45],"value":{"type":"parenthesized","parenthesized":{"range":[81,39,81,44],"value":{"type":"application","application":[{"range":[81,39,81,42],"value":{"type":"float","float":2.5}},{"range":[81,42,81,43],"value":{"type":"operator","operator":"/"}},{"range":[81,43,81,44],"value":{"type":"integer","integer":2}}]}}}},{"range":[81,46,81,53],"value":{"type":"functionOrValue","functionOrValue":{"moduleName":[],"name":"recInit"}}},{"range":[81,54,81,55],"value":{"type":"integer","integer":0}}]}}}}}}},{"range":[83,1,84,61],"value":{"type":"function","function":{"documentation":null,"signature":{"range":[83,1,83,17],"value":{"name":{"range":[83,1,83,11],"value":"ballConfig"},"typeAnnotation":{"range":[83,13,83,17],"value":{"type":"typed","typed":{"moduleNameAndName":{"range":[83,13,83,17],"value":{"moduleName":[],"name":"Ball"}},"args":[]}}}}},"declaration":{"range":[84,1,84,61],"value":{"name":{"range":[84,1,84,11],"value":"ballConfig"},"arguments":[],"expression":{"range":[84,14,84,61],"value":{"type":"application","application":[{"range":[84,14,84,18],"value":{"type":"functionOrValue","functionOrValue":{"moduleName":[],"name":"Ball"}}},{"range":[84,19,84,25],"value":{"type":"parenthesized","parenthesized":{"range":[84,20,84,24],"value":{"type":"application","application":[{"range":[84,20,84,22],"value":{"type":"integer","integer":25}},{"range":[84,22,84,23],"value":{"type":"operator","operator":"/"}},{"range":[84,23,84,24],"value":{"type":"integer","integer":2}}]}}}},{"range":[84,26,84,32],"value":{"type":"parenthesized","parenthesized":{"range":[84,27,84,31],"value":{"type":"application","application":[{"range":[84,27,84,29],"value":{"type":"integer","integer":70}},{"range":[84,29,84,30],"value":{"type":"operator","operator":"/"}},{"range":[84,30,84,31],"value":{"type":"integer","integer":2}}]}}}},{"range":[84,33,84,40],"value":{"type":"parenthesized","parenthesized":{"range":[84,34,84,39],"value":{"type":"application","application":[{"range":[84,34,84,37],"value":{"type":"float","float":1.5}},{"range":[84,37,84,38],"value":{"type":"operator","operator":"/"}},{"range":[84,38,84,39],"value":{"type":"integer","integer":2}}]}}}},{"range":[84,41,84,48],"value":{"type":"functionOrValue","functionOrValue":{"moduleName":[],"name":"recInit"}}},{"range":[84,49,84,54],"value":{"type":"parenthesized","parenthesized":{"range":[84,50,84,53],"value":{"type":"application","application":[{"range":[84,50,84,51],"value":{"type":"integer","integer":1}},{"range":[84,51,84,52],"value":{"type":"operator","operator":"/"}},{"range":[84,52,84,53],"value":{"type":"integer","integer":2}}]}}}},{"range":[84,55,84,61],"value":{"type":"parenthesized","parenthesized":{"range":[84,56,84,60],"value":{"type":"application","application":[{"range":[84,56,84,58],"value":{"type":"negation","negation":{"range":[84,57,84,58],"value":{"type":"integer","integer":1}}}},{"range":[84,58,84,59],"value":{"type":"operator","operator":"/"}},{"range":[84,59,84,60],"value":{"type":"integer","integer":2}}]}}}}]}}}}}}},{"range":[86,1,87,11],"value":{"type":"function","function":{"documentation":null,"signature":{"range":[86,1,86,12],"value":{"name":{"range":[86,1,86,6],"value":"total"},"typeAnnotation":{"range":[86,9,86,12],"value":{"type":"typed","typed":{"moduleNameAndName":{"range":[86,9,86,12],"value":{"moduleName":[],"name":"Int"}},"args":[]}}}}},"declaration":{"range":[87,1,87,11],"value":{"name":{"range":[87,1,87,6],"value":"total"},"arguments":[],"expression":{"range":[87,9,87,11],"value":{"type":"integer","integer":50}}}}}}},{"range":[89,1,90,20],"value":{"type":"function","function":{"documentation":null,"signature":{"range":[89,1,89,20],"value":{"name":{"range":[89,1,89,12],"value":"canvasWidth"},"typeAnnotation":{"range":[89,15,89,20],"value":{"type":"typed","typed":{"moduleNameAndName":{"range":[89,15,89,20],"value":{"moduleName":[],"name":"Float"}},"args":[]}}}}},"declaration":{"range":[90,1,90,20],"value":{"name":{"range":[90,1,90,12],"value":"canvasWidth"},"arguments":[],"expression":{"range":[90,15,90,20],"value":{"type":"application","application":[{"range":[90,15,90,18],"value":{"type":"integer","integer":100}},{"range":[90,18,90,19],"value":{"type":"operator","operator":"/"}},{"range":[90,19,90,20],"value":{"type":"integer","integer":2}}]}}}}}}},{"range":[91,1,92,20],"value":{"type":"function","function":{"documentation":null,"signature":{"range":[91,1,91,21],"value":{"name":{"range":[91,1,91,13],"value":"canvasHeight"},"typeAnnotation":{"range":[91,16,91,21],"value":{"type":"typed","typed":{"moduleNameAndName":{"range":[91,16,91,21],"value":{"moduleName":[],"name":"Float"}},"args":[]}}}}},"declaration":{"range":[92,1,92,20],"value":{"name":{"range":[92,1,92,13],"value":"canvasHeight"},"arguments":[],"expression":{"range":[92,16,92,20],"value":{"type":"application","application":[{"range":[92,16,92,18],"value":{"type":"integer","integer":77}},{"range":[92,18,92,19],"value":{"type":"operator","operator":"/"}},{"range":[92,19,92,20],"value":{"type":"integer","integer":2}}]}}}}}}},{"range":[93,1,94,20],"value":{"type":"function","function":{"documentation":null,"signature":{"range":[93,1,93,19],"value":{"name":{"range":[93,1,93,11],"value":"halfHeight"},"typeAnnotation":{"range":[93,14,93,19],"value":{"type":"typed","typed":{"moduleNameAndName":{"range":[93,14,93,19],"value":{"moduleName":[],"name":"Float"}},"args":[]}}}}},"declaration":{"range":[94,1,94,20],"value":{"name":{"range":[94,1,94,11],"value":"halfHeight"},"arguments":[],"expression":{"range":[94,14,94,20],"value":{"type":"application","application":[{"range":[94,14,94,18],"value":{"type":"float","float":38.5}},{"range":[94,18,94,19],"value":{"type":"operator","operator":"/"}},{"range":[94,19,94,20],"value":{"type":"integer","integer":2}}]}}}}}}},{"range":[95,1,96,17],"value":{"type":"function","function":{"documentation":null,"signature":{"range":[95,1,95,18],"value":{"name":{"range":[95,1,95,10],"value":"halfWidth"},"typeAnnotation":{"range":[95,13,95,18],"value":{"type":"typed","typed":{"moduleNameAndName":{"range":[95,13,95,18],"value":{"moduleName":[],"name":"Float"}},"args":[]}}}}},"declaration":{"range":[96,1,96,17],"value":{"name":{"range":[96,1,96,10],"value":"halfWidth"},"arguments":[],"expression":{"range":[96,13,96,17],"value":{"type":"application","application":[{"range":[96,13,96,15],"value":{"type":"integer","integer":50}},{"range":[96,15,96,16],"value":{"type":"operator","operator":"/"}},{"range":[96,16,96,17],"value":{"type":"integer","integer":2}}]}}}}}}},{"range":[99,1,110,1],"value":{"type":"function","function":{"documentation":null,"signature":{"range":[99,1,99,32],"value":{"name":{"range":[99,1,99,15],"value":"brickRecUpdate"},"typeAnnotation":{"range":[99,18,99,32],"value":{"type":"function","function":{"left":{"range":[99,18,99,23],"value":{"type":"typed","typed":{"moduleNameAndName":{"range":[99,18,99,23],"value":{"moduleName":[],"name":"Brick"}},"args":[]}}},"right":{"range":[99,27,99,32],"value":{"type":"typed","typed":{"moduleNameAndName":{"range":[99,27,99,32],"value":{"moduleName":[],"name":"Brick"}},"args":[]}}}}}}}},"declaration":{"range":[100,1,110,1],"value":{"name":{"range":[100,1,100,15],"value":"brickRecUpdate"},"arguments":[{"range":[100,16,100,21],"value":{"type":"var","var":{"value":"model"}}}],"expression":{"range":[101,5,110,1],"value":{"type":"let","let":{"declarations":[{"range":[102,9,103,9],"value":{"type":"function","function":{"documentation":null,"signature":null,"declaration":{"range":[102,9,102,32],"value":{"name":{"range":[102,9,102,14],"value":"halfx"},"arguments":[],"expression":{"range":[102,22,102,32],"value":{"type":"application","application":[{"range":[102,22,102,28],"value":{"type":"recordAccess","recordAccess":{"expression":{"range":[102,17,102,22],"value":{"type":"functionOrValue","functionOrValue":{"moduleName":[],"name":"model"}}},"name":{"range":[102,23,102,28],"value":"width"}}}},{"range":[102,29,102,30],"value":{"type":"operator","operator":"/"}},{"range":[102,31,102,32],"value":{"type":"integer","integer":2}}]}}}}}}},{"range":[103,9,104,9],"value":{"type":"function","function":{"documentation":null,"signature":null,"declaration":{"range":[103,9,103,32],"value":{"name":{"range":[103,9,103,14],"value":"halfy"},"arguments":[],"expression":{"range":[103,22,103,32],"value":{"type":"application","application":[{"range":[103,22,103,29],"value":{"type":"recordAccess","recordAccess":{"expression":{"range":[103,17,103,22],"value":{"type":"functionOrValue","functionOrValue":{"moduleName":[],"name":"model"}}},"name":{"range":[103,23,103,29],"value":"height"}}}},{"range":[103,30,103,31],"value":{"type":"operator","operator":"/"}},{"range":[103,31,103,32],"value":{"type":"integer","integer":2}}]}}}}}}},{"range":[104,9,105,9],"value":{"type":"function","function":{"documentation":null,"signature":null,"declaration":{"range":[104,9,104,31],"value":{"name":{"range":[104,9,104,13],"value":"newx"},"arguments":[],"expression":{"range":[104,21,104,31],"value":{"type":"application","application":[{"range":[104,21,104,23],"value":{"type":"recordAccess","recordAccess":{"expression":{"range":[104,16,104,21],"value":{"type":"functionOrValue","functionOrValue":{"moduleName":[],"name":"model"}}},"name":{"range":[104,22,104,23],"value":"x"}}}},{"range":[104,24,104,25],"value":{"type":"operator","operator":"+"}},{"range":[104,26,104,31],"value":{"type":"functionOrValue","functionOrValue":{"moduleName":[],"name":"halfx"}}}]}}}}}}},{"range":[105,9,106,9],"value":{"type":"function","function":{"documentation":null,"signature":null,"declaration":{"range":[105,9,105,31],"value":{"name":{"range":[105,9,105,13],"value":"newy"},"arguments":[],"expression":{"range":[105,21,105,31],"value":{"type":"application","application":[{"range":[105,21,105,23],"value":{"type":"recordAccess","recordAccess":{"expression":{"range":[105,16,105,21],"value":{"type":"functionOrValue","functionOrValue":{"moduleName":[],"name":"model"}}},"name":{"range":[105,22,105,23],"value":"y"}}}},{"range":[105,24,105,25],"value":{"type":"operator","operator":"+"}},{"range":[105,26,105,31],"value":{"type":"functionOrValue","functionOrValue":{"moduleName":[],"name":"halfy"}}}]}}}}}}},{"range":[106,9,107,5],"value":{"type":"function","function":{"documentation":null,"signature":null,"declaration":{"range":[106,9,106,43],"value":{"name":{"range":[106,9,106,15],"value":"newRec"},"arguments":[],"expression":{"range":[106,18,106,43],"value":{"type":"application","application":[{"range":[106,18,106,21],"value":{"type":"functionOrValue","functionOrValue":{"moduleName":[],"name":"Rec"}}},{"range":[106,22,106,26],"value":{"type":"functionOrValue","functionOrValue":{"moduleName":[],"name":"newx"}}},{"range":[106,27,106,31],"value":{"type":"functionOrValue","functionOrValue":{"moduleName":[],"name":"newy"}}},{"range":[106,32,106,37],"value":{"type":"functionOrValue","functionOrValue":{"moduleName":[],"name":"halfx"}}},{"range":[106,38,106,43],"value":{"type":"functionOrValue","functionOrValue":{"moduleName":[],"name":"halfy"}}}]}}}}}}}],"expression":{"range":[108,9,108,32],"value":{"type":"recordUpdate","recordUpdate":{"name":{"range":[108,11,108,16],"value":"model"},"updates":[{"range":[108,18,108,31],"value":{"field":{"range":[108,18,108,22],"value":"edge"},"expression":{"range":[108,25,108,31],"value":{"type":"functionOrValue","functionOrValue":{"moduleName":[],"name":"newRec"}}}}}]}}}}}}}}}}},{"range":[110,1,121,1],"value":{"type":"function","function":{"documentation":null,"signature":{"range":[110,1,110,26],"value":{"name":{"range":[110,1,110,13],"value":"batRecUpdate"},"typeAnnotation":{"range":[110,16,110,26],"value":{"type":"function","function":{"left":{"range":[110,16,110,19],"value":{"type":"typed","typed":{"moduleNameAndName":{"range":[110,16,110,19],"value":{"moduleName":[],"name":"Bat"}},"args":[]}}},"right":{"range":[110,23,110,26],"value":{"type":"typed","typed":{"moduleNameAndName":{"range":[110,23,110,26],"value":{"moduleName":[],"name":"Bat"}},"args":[]}}}}}}}},"declaration":{"range":[111,1,121,1],"value":{"name":{"range":[111,1,111,13],"value":"batRecUpdate"},"arguments":[{"range":[111,14,111,19],"value":{"type":"var","var":{"value":"model"}}}],"expression":{"range":[112,5,121,1],"value":{"type":"let","let":{"declarations":[{"range":[113,9,114,9],"value":{"type":"function","function":{"documentation":null,"signature":null,"declaration":{"range":[113,9,113,32],"value":{"name":{"range":[113,9,113,14],"value":"halfx"},"arguments":[],"expression":{"range":[113,22,113,32],"value":{"type":"application","application":[{"range":[113,22,113,28],"value":{"type":"recordAccess","recordAccess":{"expression":{"range":[113,17,113,22],"value":{"type":"functionOrValue","functionOrValue":{"moduleName":[],"name":"model"}}},"name":{"range":[113,23,113,28],"value":"width"}}}},{"range":[113,29,113,30],"value":{"type":"operator","operator":"/"}},{"range":[113,31,113,32],"value":{"type":"integer","integer":2}}]}}}}}}},{"range":[114,9,115,9],"value":{"type":"function","function":{"documentation":null,"signature":null,"declaration":{"range":[114,9,114,32],"value":{"name":{"range":[114,9,114,14],"value":"halfy"},"arguments":[],"expression":{"range":[114,22,114,32],"value":{"type":"application","application":[{"range":[114,22,114,29],"value":{"type":"recordAccess","recordAccess":{"expression":{"range":[114,17,114,22],"value":{"type":"functionOrValue","functionOrValue":{"moduleName":[],"name":"model"}}},"name":{"range":[114,23,114,29],"value":"height"}}}},{"range":[114,30,114,31],"value":{"type":"operator","operator":"/"}},{"range":[114,31,114,32],"value":{"type":"integer","integer":2}}]}}}}}}},{"range":[115,9,116,9],"value":{"type":"function","function":{"documentation":null,"signature":null,"declaration":{"range":[115,9,115,31],"value":{"name":{"range":[115,9,115,13],"value":"newx"},"arguments":[],"expression":{"range":[115,21,115,31],"value":{"type":"application","application":[{"range":[115,21,115,23],"value":{"type":"recordAccess","recordAccess":{"expression":{"range":[115,16,115,21],"value":{"type":"functionOrValue","functionOrValue":{"moduleName":[],"name":"model"}}},"name":{"range":[115,22,115,23],"value":"x"}}}},{"range":[115,24,115,25],"value":{"type":"operator","operator":"+"}},{"range":[115,26,115,31],"value":{"type":"functionOrValue","functionOrValue":{"moduleName":[],"name":"halfx"}}}]}}}}}}},{"range":[116,9,117,9],"value":{"type":"function","function":{"documentation":null,"signature":null,"declaration":{"range":[116,9,116,31],"value":{"name":{"range":[116,9,116,13],"value":"newy"},"arguments":[],"expression":{"range":[116,21,116,31],"value":{"type":"application","application":[{"range":[116,21,116,23],"value":{"type":"recordAccess","recordAccess":{"expression":{"range":[116,16,116,21],"value":{"type":"functionOrValue","functionOrValue":{"moduleName":[],"name":"model"}}},"name":{"range":[116,22,116,23],"value":"y"}}}},{"range":[116,24,116,25],"value":{"type":"operator","operator":"+"}},{"range":[116,26,116,31],"value":{"type":"functionOrValue","functionOrValue":{"moduleName":[],"name":"halfy"}}}]}}}}}}},{"range":[117,9,118,5],"value":{"type":"function","function":{"documentation":null,"signature":null,"declaration":{"range":[117,9,117,43],"value":{"name":{"range":[117,9,117,15],"value":"newRec"},"arguments":[],"expression":{"range":[117,18,117,43],"value":{"type":"application","application":[{"range":[117,18,117,21],"value":{"type":"functionOrValue","functionOrValue":{"moduleName":[],"name":"Rec"}}},{"range":[117,22,117,26],"value":{"type":"functionOrValue","functionOrValue":{"moduleName":[],"name":"newx"}}},{"range":[117,27,117,31],"value":{"type":"functionOrValue","functionOrValue":{"moduleName":[],"name":"newy"}}},{"range":[117,32,117,37],"value":{"type":"functionOrValue","functionOrValue":{"moduleName":[],"name":"halfx"}}},{"range":[117,38,117,43],"value":{"type":"functionOrValue","functionOrValue":{"moduleName":[],"name":"halfy"}}}]}}}}}}}],"expression":{"range":[119,9,119,32],"value":{"type":"recordUpdate","recordUpdate":{"name":{"range":[119,11,119,16],"value":"model"},"updates":[{"range":[119,18,119,31],"value":{"field":{"range":[119,18,119,22],"value":"edge"},"expression":{"range":[119,25,119,31],"value":{"type":"functionOrValue","functionOrValue":{"moduleName":[],"name":"newRec"}}}}}]}}}}}}}}}}},{"range":[121,1,129,1],"value":{"type":"function","function":{"documentation":null,"signature":{"range":[121,1,121,29],"value":{"name":{"range":[121,1,121,14],"value":"ballRecUpdate"},"typeAnnotation":{"range":[121,17,121,29],"value":{"type":"function","function":{"left":{"range":[121,17,121,21],"value":{"type":"typed","typed":{"moduleNameAndName":{"range":[121,17,121,21],"value":{"moduleName":[],"name":"Ball"}},"args":[]}}},"right":{"range":[121,25,121,29],"value":{"type":"typed","typed":{"moduleNameAndName":{"range":[121,25,121,29],"value":{"moduleName":[],"name":"Ball"}},"args":[]}}}}}}}},"declaration":{"range":[122,1,129,1],"value":{"name":{"range":[122,1,122,14],"value":"ballRecUpdate"},"arguments":[{"range":[122,15,122,20],"value":{"type":"var","var":{"value":"model"}}}],"expression":{"range":[123,5,129,1],"value":{"type":"let","let":{"declarations":[{"range":[124,9,125,5],"value":{"type":"function","function":{"documentation":null,"signature":null,"declaration":{"range":[124,9,124,53],"value":{"name":{"range":[124,9,124,15],"value":"newRec"},"arguments":[],"expression":{"range":[124,18,124,53],"value":{"type":"application","application":[{"range":[124,18,124,21],"value":{"type":"functionOrValue","functionOrValue":{"moduleName":[],"name":"Rec"}}},{"range":[124,27,124,29],"value":{"type":"recordAccess","recordAccess":{"expression":{"range":[124,22,124,27],"value":{"type":"functionOrValue","functionOrValue":{"moduleName":[],"name":"model"}}},"name":{"range":[124,28,124,29],"value":"x"}}}},{"range":[124,35,124,37],"value":{"type":"recordAccess","recordAccess":{"expression":{"range":[124,30,124,35],"value":{"type":"functionOrValue","functionOrValue":{"moduleName":[],"name":"model"}}},"name":{"range":[124,36,124,37],"value":"y"}}}},{"range":[124,43,124,45],"value":{"type":"recordAccess","recordAccess":{"expression":{"range":[124,38,124,43],"value":{"type":"functionOrValue","functionOrValue":{"moduleName":[],"name":"model"}}},"name":{"range":[124,44,124,45],"value":"r"}}}},{"range":[124,51,124,53],"value":{"type":"recordAccess","recordAccess":{"expression":{"range":[124,46,124,51],"value":{"type":"functionOrValue","functionOrValue":{"moduleName":[],"name":"model"}}},"name":{"range":[124,52,124,53],"value":"r"}}}}]}}}}}}}],"expression":{"range":[126,9,126,32],"value":{"type":"recordUpdate","recordUpdate":{"name":{"range":[126,11,126,16],"value":"model"},"updates":[{"range":[126,18,126,31],"value":{"field":{"range":[126,18,126,22],"value":"edge"},"expression":{"range":[126,25,126,31],"value":{"type":"functionOrValue","functionOrValue":{"moduleName":[],"name":"newRec"}}}}}]}}}}}}}}}}},{"range":[129,1,136,1],"value":{"type":"function","function":{"documentation":null,"signature":{"range":[129,1,129,44],"value":{"name":{"range":[129,1,129,18],"value":"genearateOneBrick"},"typeAnnotation":{"range":[129,21,129,44],"value":{"type":"function","function":{"left":{"range":[129,21,129,26],"value":{"type":"typed","typed":{"moduleNameAndName":{"range":[129,21,129,26],"value":{"moduleName":[],"name":"Float"}},"args":[]}}},"right":{"range":[129,30,129,44],"value":{"type":"function","function":{"left":{"range":[129,30,129,35],"value":{"type":"typed","typed":{"moduleNameAndName":{"range":[129,30,129,35],"value":{"moduleName":[],"name":"Float"}},"args":[]}}},"right":{"range":[129,39,129,44],"value":{"type":"typed","typed":{"moduleNameAndName":{"range":[129,39,129,44],"value":{"moduleName":[],"name":"Brick"}},"args":[]}}}}}}}}}}},"declaration":{"range":[130,1,136,1],"value":{"name":{"range":[130,1,130,18],"value":"genearateOneBrick"},"arguments":[{"range":[130,19,130,20],"value":{"type":"var","var":{"value":"x"}}},{"range":[130,21,130,22],"value":{"type":"var","var":{"value":"y"}}}],"expression":{"range":[131,5,136,1],"value":{"type":"let","let":{"declarations":[{"range":[132,9,133,5],"value":{"type":"function","function":{"documentation":null,"signature":null,"declaration":{"range":[132,9,132,97],"value":{"name":{"range":[132,9,132,18],"value":"bricktemp"},"arguments":[],"expression":{"range":[132,21,132,97],"value":{"type":"application","application":[{"range":[132,21,132,26],"value":{"type":"functionOrValue","functionOrValue":{"moduleName":[],"name":"Brick"}}},{"range":[132,27,132,28],"value":{"type":"functionOrValue","functionOrValue":{"moduleName":[],"name":"x"}}},{"range":[132,29,132,30],"value":{"type":"functionOrValue","functionOrValue":{"moduleName":[],"name":"y"}}},{"range":[132,42,132,48],"value":{"type":"recordAccess","recordAccess":{"expression":{"range":[132,31,132,42],"value":{"type":"functionOrValue","functionOrValue":{"moduleName":[],"name":"brickConfig"}}},"name":{"range":[132,43,132,48],"value":"width"}}}},{"range":[132,60,132,67],"value":{"type":"recordAccess","recordAccess":{"expression":{"range":[132,49,132,60],"value":{"type":"functionOrValue","functionOrValue":{"moduleName":[],"name":"brickConfig"}}},"name":{"range":[132,61,132,67],"value":"height"}}}},{"range":[132,68,132,75],"value":{"type":"functionOrValue","functionOrValue":{"moduleName":[],"name":"recInit"}}},{"range":[132,87,132,97],"value":{"type":"recordAccess","recordAccess":{"expression":{"range":[132,76,132,87],"value":{"type":"functionOrValue","functionOrValue":{"moduleName":[],"name":"brickConfig"}}},"name":{"range":[132,88,132,97],"value":"collision"}}}}]}}}}}}}],"expression":{"range":[134,9,134,33],"value":{"type":"application","application":[{"range":[134,9,134,23],"value":{"type":"functionOrValue","functionOrValue":{"moduleName":[],"name":"brickRecUpdate"}}},{"range":[134,24,134,33],"value":{"type":"functionOrValue","functionOrValue":{"moduleName":[],"name":"bricktemp"}}}]}}}}}}}}}},{"range":[136,1,156,1],"value":{"type":"function","function":{"documentation":null,"signature":{"range":[136,1,136,67],"value":{"name":{"range":[136,1,136,15],"value":"generateBricks"},"typeAnnotation":{"range":[136,18,136,67],"value":{"type":"function","function":{"left":{"range":[136,18,136,28],"value":{"type":"typed","typed":{"moduleNameAndName":{"range":[136,18,136,22],"value":{"moduleName":[],"name":"List"}},"args":[{"range":[136,23,136,28],"value":{"type":"typed","typed":{"moduleNameAndName":{"range":[136,23,136,28],"value":{"moduleName":[],"name":"Brick"}},"args":[]}}}]}}},"right":{"range":[136,32,136,67],"value":{"type":"function","function":{"left":{"range":[136,32,136,35],"value":{"type":"typed","typed":{"moduleNameAndName":{"range":[136,32,136,35],"value":{"moduleName":[],"name":"Int"}},"args":[]}}},"right":{"range":[136,39,136,67],"value":{"type":"function","function":{"left":{"range":[136,39,136,44],"value":{"type":"typed","typed":{"moduleNameAndName":{"range":[136,39,136,44],"value":{"moduleName":[],"name":"Float"}},"args":[]}}},"right":{"range":[136,48,136,67],"value":{"type":"function","function":{"left":{"range":[136,48,136,53],"value":{"type":"typed","typed":{"moduleNameAndName":{"range":[136,48,136,53],"value":{"moduleName":[],"name":"Float"}},"args":[]}}},"right":{"range":[136,57,136,67],"value":{"type":"typed","typed":{"moduleNameAndName":{"range":[136,57,136,61],"value":{"moduleName":[],"name":"List"}},"args":[{"range":[136,62,136,67],"value":{"type":"typed","typed":{"moduleNameAndName":{"range":[136,62,136,67],"value":{"moduleName":[],"name":"Brick"}},"args":[]}}}]}}}}}}}}}}}}}}}}},"declaration":{"range":[137,1,156,1],"value":{"name":{"range":[137,1,137,15],"value":"generateBricks"},"arguments":[{"range":[137,16,137,25],"value":{"type":"var","var":{"value":"bricklist"}}},{"range":[137,26,137,32],"value":{"type":"var","var":{"value":"number"}}},{"range":[137,33,137,34],"value":{"type":"var","var":{"value":"x"}}},{"range":[137,35,137,36],"value":{"type":"var","var":{"value":"y"}}}],"expression":{"range":[138,5,156,1],"value":{"type":"let","let":{"declarations":[{"range":[139,9,144,9],"value":{"type":"function","function":{"documentation":null,"signature":null,"declaration":{"range":[139,9,144,9],"value":{"name":{"range":[139,9,139,14],"value":"nexty"},"arguments":[{"range":[139,15,139,21],"value":{"type":"var","var":{"value":"xinput"}}},{"range":[139,22,139,28],"value":{"type":"var","var":{"value":"yinput"}}}],"expression":{"range":[140,13,144,9],"value":{"type":"ifBlock","ifBlock":{"clause":{"range":[140,16,140,57],"value":{"type":"application","application":[{"range":[140,16,140,42],"value":{"type":"parenthesized","parenthesized":{"range":[140,17,140,41],"value":{"type":"application","application":[{"range":[140,17,140,23],"value":{"type":"functionOrValue","functionOrValue":{"moduleName":[],"name":"xinput"}}},{"range":[140,23,140,24],"value":{"type":"operator","operator":"+"}},{"range":[140,35,140,41],"value":{"type":"recordAccess","recordAccess":{"expression":{"range":[140,24,140,35],"value":{"type":"functionOrValue","functionOrValue":{"moduleName":[],"name":"brickConfig"}}},"name":{"range":[140,36,140,41],"value":"width"}}}}]}}}},{"range":[140,43,140,45],"value":{"type":"operator","operator":">="}},{"range":[140,46,140,57],"value":{"type":"functionOrValue","functionOrValue":{"moduleName":[],"name":"canvasWidth"}}}]}},"then":{"range":[141,17,141,44],"value":{"type":"application","application":[{"range":[141,17,141,23],"value":{"type":"functionOrValue","functionOrValue":{"moduleName":[],"name":"yinput"}}},{"range":[141,24,141,25],"value":{"type":"operator","operator":"+"}},{"range":[141,37,141,44],"value":{"type":"recordAccess","recordAccess":{"expression":{"range":[141,26,141,37],"value":{"type":"functionOrValue","functionOrValue":{"moduleName":[],"name":"brickConfig"}}},"name":{"range":[141,38,141,44],"value":"height"}}}}]}},"else":{"range":[143,17,143,23],"value":{"type":"functionOrValue","functionOrValue":{"moduleName":[],"name":"yinput"}}}}}}}}}}},{"range":[144,9,149,9],"value":{"type":"function","function":{"documentation":null,"signature":null,"declaration":{"range":[144,9,149,9],"value":{"name":{"range":[144,9,144,14],"value":"nextx"},"arguments":[{"range":[144,15,144,21],"value":{"type":"var","var":{"value":"xinput"}}}],"expression":{"range":[145,13,149,9],"value":{"type":"ifBlock","ifBlock":{"clause":{"range":[145,16,145,56],"value":{"type":"application","application":[{"range":[145,16,145,42],"value":{"type":"parenthesized","parenthesized":{"range":[145,17,145,41],"value":{"type":"application","application":[{"range":[145,17,145,23],"value":{"type":"functionOrValue","functionOrValue":{"moduleName":[],"name":"xinput"}}},{"range":[145,23,145,24],"value":{"type":"operator","operator":"+"}},{"range":[145,35,145,41],"value":{"type":"recordAccess","recordAccess":{"expression":{"range":[145,24,145,35],"value":{"type":"functionOrValue","functionOrValue":{"moduleName":[],"name":"brickConfig"}}},"name":{"range":[145,36,145,41],"value":"width"}}}}]}}}},{"range":[145,43,145,44],"value":{"type":"operator","operator":"<"}},{"range":[145,45,145,56],"value":{"type":"functionOrValue","functionOrValue":{"moduleName":[],"name":"canvasWidth"}}}]}},"then":{"range":[146,17,146,43],"value":{"type":"application","application":[{"range":[146,17,146,23],"value":{"type":"functionOrValue","functionOrValue":{"moduleName":[],"name":"xinput"}}},{"range":[146,24,146,25],"value":{"type":"operator","operator":"+"}},{"range":[146,37,146,43],"value":{"type":"recordAccess","recordAccess":{"expression":{"range":[146,26,146,37],"value":{"type":"functionOrValue","functionOrValue":{"moduleName":[],"name":"brickConfig"}}},"name":{"range":[146,38,146,43],"value":"width"}}}}]}},"else":{"range":[148,17,148,18],"value":{"type":"integer","integer":0}}}}}}}}}},{"range":[149,9,150,5],"value":{"type":"function","function":{"documentation":null,"signature":null,"declaration":{"range":[149,9,149,26],"value":{"name":{"range":[149,9,149,14],"value":"ytemp"},"arguments":[],"expression":{"range":[149,17,149,26],"value":{"type":"application","application":[{"range":[149,17,149,22],"value":{"type":"functionOrValue","functionOrValue":{"moduleName":[],"name":"nexty"}}},{"range":[149,23,149,24],"value":{"type":"functionOrValue","functionOrValue":{"moduleName":[],"name":"x"}}},{"range":[149,25,149,26],"value":{"type":"functionOrValue","functionOrValue":{"moduleName":[],"name":"y"}}}]}}}}}}}],"expression":{"range":[151,9,156,1],"value":{"type":"ifBlock","ifBlock":{"clause":{"range":[151,12,151,23],"value":{"type":"application","application":[{"range":[151,12,151,18],"value":{"type":"functionOrValue","functionOrValue":{"moduleName":[],"name":"number"}}},{"range":[151,19,151,21],"value":{"type":"operator","operator":"=="}},{"range":[151,22,151,23],"value":{"type":"integer","integer":0}}]}},"then":{"range":[152,13,152,22],"value":{"type":"functionOrValue","functionOrValue":{"moduleName":[],"name":"bricklist"}}},"else":{"range":[154,13,154,96],"value":{"type":"application","application":[{"range":[154,13,154,27],"value":{"type":"functionOrValue","functionOrValue":{"moduleName":[],"name":"generateBricks"}}},{"range":[154,28,154,67],"value":{"type":"parenthesized","parenthesized":{"range":[154,31,154,65],"value":{"type":"application","application":[{"range":[154,31,154,48],"value":{"type":"functionOrValue","functionOrValue":{"moduleName":[],"name":"genearateOneBrick"}}},{"range":[154,49,154,50],"value":{"type":"functionOrValue","functionOrValue":{"moduleName":[],"name":"x"}}},{"range":[154,51,154,52],"value":{"type":"functionOrValue","functionOrValue":{"moduleName":[],"name":"y"}}},{"range":[154,53,154,55],"value":{"type":"operator","operator":"::"}},{"range":[154,56,154,65],"value":{"type":"functionOrValue","functionOrValue":{"moduleName":[],"name":"bricklist"}}}]}}}},{"range":[154,68,154,80],"value":{"type":"parenthesized","parenthesized":{"range":[154,69,154,79],"value":{"type":"application","application":[{"range":[154,69,154,75],"value":{"type":"functionOrValue","functionOrValue":{"moduleName":[],"name":"number"}}},{"range":[154,76,154,78],"value":{"type":"operator","operator":"-"}},{"range":[154,78,154,79],"value":{"type":"integer","integer":1}}]}}}},{"range":[154,81,154,90],"value":{"type":"parenthesized","parenthesized":{"range":[154,82,154,89],"value":{"type":"application","application":[{"range":[154,82,154,87],"value":{"type":"functionOrValue","functionOrValue":{"moduleName":[],"name":"nextx"}}},{"range":[154,88,154,89],"value":{"type":"functionOrValue","functionOrValue":{"moduleName":[],"name":"x"}}}]}}}},{"range":[154,91,154,96],"value":{"type":"functionOrValue","functionOrValue":{"moduleName":[],"name":"ytemp"}}}]}}}}}}}}}}}}}],"comments":[{"range":[79,1,79,58],"value":"-- batConfig = Bat (45/2) (70/2) (20/2) (2.5/2) recInit 0"},{"range":[78,1,78,19],"value":"-- batConfig : Bat"},{"range":[67,5,67,28],"value":"-- , canvasHeight : Int"},{"range":[66,5,66,27],"value":"-- , canvasWidth : Int"},{"range":[57,5,57,30],"value":"--size : ( Float, Float )"}]}